SshSysMon-0.2.3.data/scripts/sshmon
sshsysmon/__init__.py
sshsysmon/__main__.py
sshsysmon/sshmon.py
sshsysmon/channels/command.py
sshsysmon/channels/email.py
sshsysmon/channels/readme.md
sshsysmon/channels/stdout.py
sshsysmon/channels/webhook.py
sshsysmon/drivers/local.py
sshsysmon/drivers/readme.md
sshsysmon/drivers/ssh.py
sshsysmon/inspectors/disk.py
sshsysmon/inspectors/exec.py
sshsysmon/inspectors/filemeta.py
sshsysmon/inspectors/http.py
sshsysmon/inspectors/loadavg.py
sshsysmon/inspectors/memory.py
sshsysmon/inspectors/network.py
sshsysmon/inspectors/process.py
sshsysmon/inspectors/readme.md
sshsysmon/inspectors/system.py
sshsysmon/inspectors/tcp.py
sshsysmon/lib/__init__.py
sshsysmon/lib/monitor/__init__.py
sshsysmon/lib/monitor/alert.py
sshsysmon/lib/monitor/channelgroup.py
sshsysmon/lib/monitor/server.py
sshsysmon/lib/plugins/__init__.py
sshsysmon/lib/plugins/channel.py
sshsysmon/lib/plugins/driver.py
sshsysmon/lib/plugins/inspector.py
sshsysmon/lib/util/__init__.py
sshsysmon/lib/util/dictlib.py
sshsysmon/lib/util/parsers.py
sshsysmon/lib/util/sanitization.py
sshsysmon/lib/util/size.py
sshsysmon/lib/util/timespan.py
sshsysmon/templates/__init__.py
sshsysmon/templates/html.hb
sshsysmon/templates/htmldash.hb
sshsysmon/templates/md.hb
sshsysmon/templates/readme.md
SshSysMon-0.2.3.dist-info/LICENSE.txt
SshSysMon-0.2.3.dist-info/METADATA
SshSysMon-0.2.3.dist-info/WHEEL
SshSysMon-0.2.3.dist-info/top_level.txt
SshSysMon-0.2.3.dist-info/RECORD
