Metadata-Version: 2.1
Name: SshSysMon
Version: 0.2.3
Summary: Ssh Unix System Monitoring
Home-page: https://github.com/zix99/sshsysmon
Author: Chris LaPointe
Author-email: chris@zdyn.net
License: MIT
Keywords: monitoring,ssh,linux,unix
Platform: UNKNOWN
Requires-Dist: paramiko (==1.16.0)
Requires-Dist: pyaml (==15.8.2)
Requires-Dist: pybars3 (==0.9.1)
